{"textures":{"1":"modelengine:entity/quest_bag","2":"modelengine:entity/halfling"},"elements":[{"from":[11.017235,4.974306,5.4420276],"to":[15.017236,9.974306,10.442027],"faces":{"east":{"uv":[0.0,0.0,5.0,5.0],"tintindex":0,"rotation":0,"texture":"#1"},"south":{"uv":[5.0,5.0,9.0,10.0],"tintindex":0,"rotation":0,"texture":"#1"},"north":{"uv":[5.0,0.0,9.0,5.0],"tintindex":0,"rotation":0,"texture":"#1"},"west":{"uv":[0.0,5.0,5.0,10.0],"tintindex":0,"rotation":0,"texture":"#1"},"up":{"uv":[13.0,5.0,9.0,0.0],"tintindex":0,"rotation":0,"texture":"#1"},"down":{"uv":[13.0,5.0,9.0,10.0],"tintindex":0,"rotation":0,"texture":"#1"}},"rotation":{"origin":[2.0172358,10.724306,8.942027],"angle":0.0,"axis":"x"}},{"from":[9.421784,5.879547,6.0],"to":[12.421784,8.879547,10.0],"faces":{"east":{"uv":[0.75,7.5,1.75,8.25],"tintindex":0,"rotation":0,"texture":"#2"},"south":{"uv":[5.0,8.25,5.75,9.0],"tintindex":0,"rotation":0,"texture":"#2"},"north":{"uv":[0.75,8.25,1.5,9.0],"tintindex":0,"rotation":0,"texture":"#2"},"west":{"uv":[7.25,7.75,8.25,8.5],"tintindex":0,"rotation":0,"texture":"#2"},"up":{"uv":[8.75,1.0,8.0,0.0],"tintindex":0,"rotation":0,"texture":"#2"},"down":{"uv":[8.75,1.0,8.0,2.0],"tintindex":0,"rotation":0,"texture":"#2"}},"rotation":{"origin":[10.421784,7.379547,8.0],"angle":22.5,"axis":"z"}},{"from":[15.017236,5.974306,6.4420276],"to":[17.017235,8.974306,9.442027],"faces":{"east":{"uv":[0.0,10.0,3.0,13.0],"tintindex":0,"rotation":0,"texture":"#1"},"south":{"uv":[8.0,10.0,10.0,13.0],"tintindex":0,"rotation":0,"texture":"#1"},"north":{"uv":[6.0,10.0,8.0,13.0],"tintindex":0,"rotation":0,"texture":"#1"},"west":{"uv":[3.0,10.0,6.0,13.0],"tintindex":0,"rotation":0,"texture":"#1"},"up":{"uv":[12.0,13.0,10.0,10.0],"tintindex":0,"rotation":0,"texture":"#1"},"down":{"uv":[14.0,10.0,12.0,13.0],"tintindex":0,"rotation":0,"texture":"#1"}},"rotation":{"origin":[2.0172358,10.724306,8.942027],"angle":0.0,"axis":"x"}}],"display":{"gui":{"rotation":[30,225,0]}}}