{"textures":{"0":"modelengine:entity/dragon_blue"},"elements":[{"from":[13.563049,13.604167,8.501927],"to":[14.563049,14.604167,16.501928],"faces":{"east":{"uv":[0.25,1.25,0.75,1.75],"tintindex":0,"rotation":0,"texture":"#0"},"south":{"uv":[0.25,1.25,0.75,1.75],"tintindex":0,"rotation":0,"texture":"#0"},"north":{"uv":[0.25,1.25,0.75,1.75],"tintindex":0,"rotation":0,"texture":"#0"},"west":{"uv":[0.25,1.25,0.75,1.75],"tintindex":0,"rotation":0,"texture":"#0"},"up":{"uv":[0.25,1.25,0.75,1.75],"tintindex":0,"rotation":0,"texture":"#0"},"down":{"uv":[0.25,1.25,0.75,1.75],"tintindex":0,"rotation":0,"texture":"#0"}},"rotation":{"origin":[7.833388,14.104167,7.882172],"angle":-45.0,"axis":"z"}},{"from":[8.437059,7.5208335,7.4290833],"to":[16.43706,8.354167,8.262417],"faces":{"east":{"uv":[0.75,1.25,0.25,1.75],"tintindex":0,"rotation":0,"texture":"#0"},"south":{"uv":[0.75,1.25,0.25,1.75],"tintindex":0,"rotation":0,"texture":"#0"},"north":{"uv":[0.75,1.25,0.25,1.75],"tintindex":0,"rotation":0,"texture":"#0"},"west":{"uv":[0.75,1.25,0.25,1.75],"tintindex":0,"rotation":0,"texture":"#0"},"up":{"uv":[0.75,1.25,0.25,1.75],"tintindex":0,"rotation":0,"texture":"#0"},"down":{"uv":[0.75,1.25,0.25,1.75],"tintindex":0,"rotation":0,"texture":"#0"}}},{"from":[8.270392,7.8541665,8.262417],"to":[23.103725,7.8541665,24.59575],"faces":{"east":{"uv":[0.0,7.0,8.0,16.0],"tintindex":0,"rotation":0,"texture":"#0"},"south":{"uv":[0.0,7.0,8.0,16.0],"tintindex":0,"rotation":0,"texture":"#0"},"north":{"uv":[0.0,7.0,8.0,16.0],"tintindex":0,"rotation":0,"texture":"#0"},"west":{"uv":[0.0,7.0,8.0,16.0],"tintindex":0,"rotation":0,"texture":"#0"},"up":{"uv":[0.0,7.0,8.0,16.0],"tintindex":0,"rotation":0,"texture":"#0"},"down":{"uv":[0.0,16.0,8.0,7.0],"tintindex":0,"rotation":0,"texture":"#0"}}},{"from":[13.311854,7.4375,13.667402],"to":[14.145187,8.270833,21.667402],"faces":{"east":{"uv":[0.25,1.25,0.75,1.75],"tintindex":0,"rotation":0,"texture":"#0"},"south":{"uv":[0.25,1.25,0.75,1.75],"tintindex":0,"rotation":0,"texture":"#0"},"north":{"uv":[0.25,1.25,0.75,1.75],"tintindex":0,"rotation":0,"texture":"#0"},"west":{"uv":[0.25,1.25,0.75,1.75],"tintindex":0,"rotation":0,"texture":"#0"},"up":{"uv":[0.25,1.25,0.75,1.75],"tintindex":0,"rotation":0,"texture":"#0"},"down":{"uv":[0.25,1.25,0.75,1.75],"tintindex":0,"rotation":0,"texture":"#0"}}},{"from":[14.647006,7.6041665,10.894117],"to":[19.647007,8.270833,11.560784],"faces":{"east":{"uv":[0.25,1.25,0.75,1.75],"tintindex":0,"rotation":0,"texture":"#0"},"south":{"uv":[0.25,1.25,0.75,1.75],"tintindex":0,"rotation":0,"texture":"#0"},"north":{"uv":[0.25,1.25,0.75,1.75],"tintindex":0,"rotation":0,"texture":"#0"},"west":{"uv":[0.25,1.25,0.75,1.75],"tintindex":0,"rotation":0,"texture":"#0"},"up":{"uv":[0.25,1.25,0.75,1.75],"tintindex":0,"rotation":0,"texture":"#0"},"down":{"uv":[0.25,1.25,0.75,1.75],"tintindex":0,"rotation":0,"texture":"#0"}},"rotation":{"origin":[19.647007,7.9375,11.227451],"angle":-45.0,"axis":"y"}},{"from":[19.48034,7.6875,11.227451],"to":[27.813673,8.1875,11.727451],"faces":{"east":{"uv":[0.75,1.25,0.25,1.75],"tintindex":0,"rotation":0,"texture":"#0"},"south":{"uv":[0.75,1.25,0.25,1.75],"tintindex":0,"rotation":0,"texture":"#0"},"north":{"uv":[0.75,1.25,0.25,1.75],"tintindex":0,"rotation":0,"texture":"#0"},"west":{"uv":[0.75,1.25,0.25,1.75],"tintindex":0,"rotation":0,"texture":"#0"},"up":{"uv":[0.75,1.25,0.25,1.75],"tintindex":0,"rotation":0,"texture":"#0"},"down":{"uv":[0.75,1.25,0.25,1.75],"tintindex":0,"rotation":0,"texture":"#0"}},"rotation":{"origin":[19.647007,7.9375,11.227451],"angle":-45.0,"axis":"y"}}],"display":{"gui":{"rotation":[30,225,0]}}}